NuRadioReco/__init__.py
NuRadioReco/autodoc/Makefile
NuRadioReco/autodoc/NuRadioReco.detector.ARA.rst
NuRadioReco/autodoc/NuRadioReco.detector.ARIANNA.rst
NuRadioReco/autodoc/NuRadioReco.detector.rst
NuRadioReco/autodoc/NuRadioReco.eventbrowser.apps.rst
NuRadioReco/autodoc/NuRadioReco.eventbrowser.rst
NuRadioReco/autodoc/NuRadioReco.framework.rst
NuRadioReco/autodoc/NuRadioReco.modules.ARA.rst
NuRadioReco/autodoc/NuRadioReco.modules.ARIANNA.rst
NuRadioReco/autodoc/NuRadioReco.modules.base.rst
NuRadioReco/autodoc/NuRadioReco.modules.custom.deltaT.rst
NuRadioReco/autodoc/NuRadioReco.modules.custom.rst
NuRadioReco/autodoc/NuRadioReco.modules.io.araroot.rst
NuRadioReco/autodoc/NuRadioReco.modules.io.coreas.rst
NuRadioReco/autodoc/NuRadioReco.modules.io.noise.rst
NuRadioReco/autodoc/NuRadioReco.modules.io.rst
NuRadioReco/autodoc/NuRadioReco.modules.io.snowshovel.rst
NuRadioReco/autodoc/NuRadioReco.modules.phasedarray.rst
NuRadioReco/autodoc/NuRadioReco.modules.rst
NuRadioReco/autodoc/NuRadioReco.modules.trigger.rst
NuRadioReco/autodoc/NuRadioReco.rst
NuRadioReco/autodoc/NuRadioReco.utilities.rst
NuRadioReco/autodoc/arianna_detector_db.json
NuRadioReco/autodoc/conf.py
NuRadioReco/autodoc/includeme.rst
NuRadioReco/autodoc/index.rst
NuRadioReco/autodoc/logo_small.png
NuRadioReco/autodoc/make.bat
NuRadioReco/autodoc/modules.rst
NuRadioReco/autodoc/custom_scripts/styling.css
NuRadioReco/autodoc/pages/code_documentation.rst
NuRadioReco/autodoc/pages/contributing.rst
NuRadioReco/autodoc/pages/detector.rst
NuRadioReco/autodoc/pages/detector_database_fields.rst
NuRadioReco/autodoc/pages/event_display.rst
NuRadioReco/autodoc/pages/event_structure.rst
NuRadioReco/autodoc/pages/installation.rst
NuRadioReco/autodoc/pages/introduction.rst
NuRadioReco/autodoc/pages/nur_modules.rst
NuRadioReco/autodoc/pages/orientation_sketch.png
NuRadioReco/autodoc/pages/utilities.rst
NuRadioReco/detector/.gitignore
NuRadioReco/detector/__init__.py
NuRadioReco/detector/amp.py
NuRadioReco-1.2.dist-info/LICENSE
NuRadioReco-1.2.dist-info/WHEEL
NuRadioReco-1.2.dist-info/METADATA
NuRadioReco-1.2.dist-info/RECORD
